epitools/__init__.py
epitools/_reader.py
epitools/_sample_data.py
epitools/_version.py
epitools/_writer.py
epitools/main.py
epitools/napari.yaml
epitools/_datasets/8bitDataset/test_image.tif
epitools/analysis/__init__.py
epitools/analysis/cell_statistics.py
epitools/analysis/projection.py
epitools/analysis/segmentation.py
epitools/widgets/__init__.py
epitools/widgets/cell_statistics.py
epitools/widgets/dialogue.py
epitools/widgets/projection.py
epitools/widgets/projection_2ch.py
epitools/widgets/quality_metrics.py
epitools/widgets/segmentation.py
epitools-0.0.13.dist-info/LICENCE.md
epitools-0.0.13.dist-info/METADATA
epitools-0.0.13.dist-info/WHEEL
epitools-0.0.13.dist-info/entry_points.txt
epitools-0.0.13.dist-info/top_level.txt
epitools-0.0.13.dist-info/RECORD
