Metadata-Version: 2.2
Name: epitools
Version: 0.0.13
Summary: Quantifying 2D cell shape and epithelial tissue dynamics
Home-page: https://www.ucl.ac.uk/lmcb/users/yanlan-mao
Author: Yanlan Mao
Author-email: "Daniel R. Matthews" <d.matthews@ucl.ac.uk>, Giulia Paci <g.paci@ucl.ac.uk>, Pablo Vicente Munuera <p.munuera@ucl.ac.uk>, "Patrick J. Roddy" <patrick.roddy@ucl.ac.uk>, "Paul J. Smith" <paul.j.smith@ucl.ac.uk>, Yanlan Mao <y.mao@ucl.ac.uk>
License: BSD 3-Clause Licence
Project-URL: Code, https://github.com/epitools/epitools
Project-URL: Download, https://pypi.org/project/epitools
Project-URL: Homepage, https://github.com/epitools/epitools
Project-URL: Issues, https://github.com/epitools/epitools/issues
Keywords: biology,cell,mechanics,shape,tissue,topology
Classifier: Framework :: napari
Classifier: Intended Audience :: Science/Research
Classifier: License :: OSI Approved :: BSD License
Classifier: Operating System :: OS Independent
Classifier: Programming Language :: Python :: 3
Classifier: Programming Language :: Python :: 3 :: Only
Classifier: Programming Language :: Python :: 3.9
Classifier: Programming Language :: Python :: 3.10
Classifier: Programming Language :: Python
Classifier: Topic :: Scientific/Engineering :: Image Processing
Classifier: Topic :: Scientific/Engineering :: Medical Science Apps.
Classifier: Topic :: Scientific/Engineering :: Bio-Informatics
Requires-Python: >=3.9
License-File: LICENCE.md
Requires-Dist: PartSeg
Requires-Dist: magicgui
Requires-Dist: matplotlib
Requires-Dist: napari
Requires-Dist: networkx
Requires-Dist: numpy
Requires-Dist: pandas
Requires-Dist: scikit-image>=0.20
Requires-Dist: scipy
Provides-Extra: dev
Requires-Dist: black; extra == "dev"
Requires-Dist: mypy; extra == "dev"
Requires-Dist: pre-commit; extra == "dev"
Requires-Dist: pyqt5; extra == "dev"
Requires-Dist: ruff; extra == "dev"
Requires-Dist: tox; extra == "dev"
Provides-Extra: docs
Requires-Dist: myst-parser; extra == "docs"
Requires-Dist: pydata-sphinx-theme; extra == "docs"
Requires-Dist: pytz; extra == "docs"
Requires-Dist: sphinx-autobuild; extra == "docs"
Requires-Dist: sphinx<5; extra == "docs"
Requires-Dist: sphinx_autodoc_typehints; extra == "docs"
Requires-Dist: sphinxcontrib-video; extra == "docs"
Requires-Dist: types-pytz; extra == "docs"
Provides-Extra: wf
Requires-Dist: btrack[napari]>=0.6.1; extra == "wf"
Requires-Dist: napari-segment-blobs-and-things-with-membranes; extra == "wf"
